logfunc/__init__.py
logfunc/config.py
logfunc/defaults.py
logfunc/main.py
logfunc/msgs.py
logfunc/utils.py
logfunc/version.py
logfunc-3.0.0.dist-info/licenses/LICENSE
logfunc-3.0.0.dist-info/METADATA
logfunc-3.0.0.dist-info/WHEEL
logfunc-3.0.0.dist-info/top_level.txt
logfunc-3.0.0.dist-info/RECORD
