Metadata-Version: 2.4
Name: logfunc
Version: 3.0.0
Summary: An EASY TO USE function decorator for advanced logging of function execution, including arguments, return values, and execution time.
Author-email: Cary Carter <ccarterdev@gmail.com>
Project-URL: Documentation, https://github.com/cc-d/logf/
Project-URL: Homepage, https://github.com/cc-d/logf/
Project-URL: Repository, https://github.com/cc-d/logf/
Project-URL: Changelog, https://github.com/cc-d/logf/blob/main/CHANGELOG.md
Classifier: Development Status :: 3 - Alpha
Classifier: Intended Audience :: Developers
Classifier: Programming Language :: Python :: 3
Classifier: Programming Language :: Python :: 3.5
Classifier: Programming Language :: Python :: 3.6
Classifier: Programming Language :: Python :: 3.7
Classifier: Programming Language :: Python :: 3.8
Classifier: Programming Language :: Python :: 3.9
Classifier: Programming Language :: Python :: 3.10
Classifier: Programming Language :: Python :: 3.11
Classifier: Programming Language :: Python :: 3.12
License-File: LICENSE
Provides-Extra: dev
Requires-Dist: pytest<8.4,>6; extra == "dev"
Requires-Dist: pytest-asyncio<0.27; extra == "dev"
Requires-Dist: pytest-cov<6.2; extra == "dev"
Requires-Dist: pytest-html<4.1.1; extra == "dev"
Requires-Dist: pytest-metadata<3.2; extra == "dev"
Requires-Dist: pytest-xdist<3.6.2; extra == "dev"
Dynamic: license-file
